README.txt
setup.py
Products/__init__.py
Products.googlecoop.egg-info/PKG-INFO
Products.googlecoop.egg-info/SOURCES.txt
Products.googlecoop.egg-info/dependency_links.txt
Products.googlecoop.egg-info/entry_points.txt
Products.googlecoop.egg-info/namespace_packages.txt
Products.googlecoop.egg-info/not-zip-safe
Products.googlecoop.egg-info/paster_plugins.txt
Products.googlecoop.egg-info/requires.txt
Products.googlecoop.egg-info/top_level.txt
Products/googlecoop/__init__.py
Products/googlecoop/configure.zcml
Products/googlecoop/interfaces.py
Products/googlecoop/setuphandlers.py
Products/googlecoop/tests.py
Products/googlecoop/utils.py
Products/googlecoop/vocabularies.py
Products/googlecoop/browser/__init__.py
Products/googlecoop/browser/configure.zcml
Products/googlecoop/browser/cseannotationsview.pt
Products/googlecoop/browser/cseannotationsview.py
Products/googlecoop/browser/csecontextview.pt
Products/googlecoop/browser/csecontextview.py
Products/googlecoop/browser/csetopicview.pt
Products/googlecoop/browser/csetopicview.py
Products/googlecoop/browser/googlecoopview.pt
Products/googlecoop/browser/googlecoopview.py
Products/googlecoop/browser/settings.py
Products/googlecoop/browser/utils.py
Products/googlecoop/browser/viewlets.py
Products/googlecoop/profiles/default/Products.googlecoop_various.txt
Products/googlecoop/profiles/default/controlpanel.xml
Products/googlecoop/profiles/default/cssregistry.xml
Products/googlecoop/profiles/default/metadata.xml
Products/googlecoop/profiles/default/registry.xml
Products/googlecoop/profiles/default/skins.xml
Products/googlecoop/profiles/default/types/Topic.xml
Products/googlecoop/skins/googlecoop_images/googlecoop-loader.gif
Products/googlecoop/skins/googlecoop_styles/google-cse-default.css
docs/HISTORY.txt
docs/INSTALL.txt
docs/LICENSE.GPL
docs/LICENSE.txt