Metadata-Version: 1.0
Name: Products.googlecoop
Version: 2.1
Summary: Google Coop for Plone makes it easy for you to integrate a Google Co-op Custom Search engine in your plone site.
Home-page: http://plone.org/products/google-co-op
Author: Christian Ledermann
Author-email: christian.ledermann@gmail.com
License: GPL
Keywords: search google
Platform: UNKNOWN
Classifier: Framework :: Plone
Classifier: Framework :: Plone :: 4.0
Classifier: Framework :: Plone :: 4.1
Classifier: Programming Language :: Python
Classifier: License :: OSI Approved :: GNU General Public License (GPL)
Classifier: Development Status :: 5 - Production/Stable
